filtermaker/__init__.py
filtermaker/filters.py
filtermaker-0.0.1.dist-info/LICENSE
filtermaker-0.0.1.dist-info/METADATA
filtermaker-0.0.1.dist-info/WHEEL
filtermaker-0.0.1.dist-info/top_level.txt
filtermaker-0.0.1.dist-info/RECORD
